moodle_questions/__init__.py
moodle_questions/answer.py
moodle_questions/dragitem.py
moodle_questions/dropzone.py
moodle_questions/quiz.py
moodle_questions/utils.py
moodle_questions/questions/__init__.py
moodle_questions/questions/calculated.py
moodle_questions/questions/calculatedmultichoice.py
moodle_questions/questions/calculatedsimple.py
moodle_questions/questions/draganddropintotext.py
moodle_questions/questions/draganddropmarkers.py
moodle_questions/questions/draganddropontoimage.py
moodle_questions/questions/essay.py
moodle_questions/questions/matching.py
moodle_questions/questions/multiplechoice.py
moodle_questions/questions/numerical.py
moodle_questions/questions/randomshortanswermatching.py
moodle_questions/questions/selectmissingwords.py
moodle_questions/questions/shortanswer.py
moodle_questions/questions/truefalse.py
moodle_questions/questions/abstract/__init__.py
moodle_questions/questions/abstract/draganddrop.py
moodle_questions/questions/abstract/question.py
moodle_questions-0.2.1.dist-info/METADATA
moodle_questions-0.2.1.dist-info/WHEEL
moodle_questions-0.2.1.dist-info/top_level.txt
moodle_questions-0.2.1.dist-info/RECORD
