Metadata-Version: 2.1
Name: moodle-questions
Version: 0.2.1
Summary: Library for manipulating questions in Moodle XML format.
Home-page: https://github.com/gethvi/moodle-questions
Author: Gethvi
Author-email: UNKNOWN
License: UNKNOWN
Platform: UNKNOWN
